octo_client/__init__.py
octo_client/client.py
octo_client/const.py
octo_client/exceptions.py
octo_client/models.py
octo_client/utils.py
octo_api_client-1.1.7.dist-info/WHEEL
octo_api_client-1.1.7.dist-info/METADATA
octo_api_client-1.1.7.dist-info/RECORD
