Metadata-Version: 2.1
Name: octo-api-client
Version: 1.1.7
Summary: HTTP client for OCTo (Open Connection for Tourism) APIs.
License: MIT
Author: Tiqets
Author-email: connections@tiqets.com
Requires-Python: >=3.7,<4.0
Classifier: License :: OSI Approved :: MIT License
Classifier: Programming Language :: Python :: 3
Classifier: Programming Language :: Python :: 3.7
Classifier: Programming Language :: Python :: 3.8
Classifier: Programming Language :: Python :: 3.9
Classifier: Programming Language :: Python :: 3.10
Classifier: Programming Language :: Python :: 3.11
Requires-Dist: requests (>=2.20.0,<3)
Requires-Dist: tonalite (>=1.7.1,<2)
